build/lib/fide_trf/__init__.py
build/lib/fide_trf/player.py
build/lib/fide_trf/tournament.py
fide_trf/__init__.py
fide_trf/player.py
fide_trf/tournament.py
FIDE_TRF-0.1.dev1.dist-info/LICENSE
FIDE_TRF-0.1.dev1.dist-info/METADATA
FIDE_TRF-0.1.dev1.dist-info/WHEEL
FIDE_TRF-0.1.dev1.dist-info/top_level.txt
FIDE_TRF-0.1.dev1.dist-info/RECORD
