Metadata-Version: 2.1
Name: FIDE-TRF
Version: 0.1.dev1
Summary: Tournament Report File format parser for the FIDE's agreed general data-exchange format for tournament resutls.
Author-email: Dionisio E Alonso <dalonso@grulic.org.ar>
License: GPL-3.0-or-later
Project-URL: Source, https://gitlab.com/baco/fide-trf
Classifier: License :: OSI Approved :: GNU General Public License v3 or later (GPLv3+)
Classifier: Operating System :: OS Independent
Classifier: Programming Language :: Python :: 3 :: Only
Classifier: Programming Language :: Python :: 3.6
Classifier: Topic :: Terminals
Classifier: Topic :: Utilities
Requires-Python: >=3.6
License-File: LICENSE
